errors/__init__.py
errors/attribute_error.py
errors/index_error.py
errors/key_error.py
errors/module_not_found_error.py
errors/name_error.py
errors/type_error.py
errors/value_error.py
errors/zero_division_error.py
errorx-0.2.0.dist-info/licenses/LICENSE
errorx-0.2.0.dist-info/METADATA
errorx-0.2.0.dist-info/WHEEL
errorx-0.2.0.dist-info/top_level.txt
errorx-0.2.0.dist-info/RECORD
